Workbook

Sheet P&L
A1: KRTRIMAIQ COGNITIVE SOLUTIONS
A2: (Partnership Firm)
A3: (Address: No. 98/A 3Rd Floor, 30Th Cross,7Th Block Jayanagar, Bangalore, KARNATAKA - 560082)
A4: Balance Sheet as at 31 March 2026
A5: Statement of Profit and loss for the year ended 31 March 2026
D6: (In Rs)
A7: Particulars | B7: Note | C7: 46112 | D7: 45747
A9: Revenue from Operations | B9: =Notes!A223 -> 10 | C9: =Notes!$I$229 -> 56778956 | D9: =Notes!$J$229 -> 0
A10: Other Income | B10: =Notes!A232 -> 11 | C10: =Notes!$I$238 -> 198358.69 | D10: =Notes!$J$238 -> 0
A11: Total Income | C11: =SUM(C9:C10) -> 56977315 | D11: =SUM(D9:D10) -> 0
A13: Expenses
A14: Employee Benefit Expenses | B14: =Notes!A241 -> 12 | C14: =Notes!$I$249 -> 40189768 | D14: =Notes!$J$249 -> 0
A15: Finance Costs | B15: =Notes!A252 -> 13 | C15: =Notes!$I$257 -> 27071.62 | D15: =Notes!$J$257 -> 0
A16: Depreciation and Amortization Expenses | B16: =Notes!A260 -> 14 | C16: =Notes!$I$265 -> 0 | D16: =Notes!$J$265 -> 0
A17: Other Expenses | B17: =Notes!A268 -> 15 | C17: =Notes!$I$299 -> 10177874 | D17: =Notes!$J$299 -> 0
A18: Total expenses | C18: =SUM(C14:C17) -> 50394714 | D18: =SUM(D14:D17) -> 0
A20: Profit/(Loss) before Exceptional and Extraordinary Item and Tax | C20: =C11-C18 -> 6582601.3 | D20: =D11-D18 -> 0
A21: Exceptional Item | C21: 0 | D21: 0
A22: Profit/(Loss) before Extraordinary Item and Tax | C22: =C20-C21 -> 6582601.3 | D22: =D20-D21 -> 0
A23: Extraordinary Item | C23: 0 | D23: 0
A24: Profit/(Loss) before Tax | C24: =C22-C23 -> 6582601.3 | D24: =D22-D23 -> 0
A25: Tax Expenses | B25: =Notes!A302 -> 16
A26: - Current Tax | C26: =Notes!$I$305 -> 0 | D26: =Notes!$J$305 -> 0
A27: - Deferred Tax | C27: =Notes!$I$306 -> 0 | D27: =Notes!$J$306 -> 0
A28: Profit/(Loss) after Tax | C28: =C24-C26-C27 -> 6582601.3 | D28: =D24-D26-D27 -> 0
A29: Earnings Per Share (Face Value per Share Rs.10 each)
A30: -Basic (In Rs)
A31: -Diluted (In Rs)
A33: See accompanying notes to the financial statements
A35: As per our report of even date | D35: For and on behalf of the Partners of
A36: For R.K.Tantry & Co., | D36: KRTRIMAIQ COGNITIVE SOLUTIONS
A37: Chartered Accountants
A38: Firm's Registration No. 004335S
A42: Radhakrishna Tantry | B42: SRINIVAS RAO POLADI
A43: Partner | B43: PARTNER
A44: Membership No. 024012
A45: UDIN:
A46: Place: Bangalore | D46: Place: Bangalore
A47: Date: | D47: Date:

Sheet BS
A1: KRTRIMAIQ COGNITIVE SOLUTIONS
A2: (Partnership Firm)
A3: (Address: No. 98/A 3Rd Floor, 30Th Cross,7Th Block Jayanagar, Bangalore, KARNATAKA - 560082)
A4: Balance Sheet as at 31 March 2026
D5: (In Rs)
A6: Particulars | B6: Note | C6: 46112 | D6: 45747
A8: I. EQUITY AND LIABILITIES
A9: (1) Partners' funds
A10: (a) Capital Account | B10: =Notes!A6 -> 1 | C10: =Notes!$I$15 -> -6761000.4 | D10: =Notes!$J$15 -> 0
A11: (b) Profit and Loss Account | B11: =Notes!A18 -> 2 | C11: =Notes!$I$23 -> 6582601.3 | D11: =Notes!$J$23 -> 0
A12: Total | C12: =SUM(C10:C11) -> -178399.09 | D12: =SUM(D10:D11) -> 0 | E12: 218775
A14: (2) Non-current liabilities
A15: (a) Long-term Borrowings | B15: =Notes!A26 -> 3 | C15: =Notes!$I$31 -> 5100000 | D15: =Notes!$J$31 -> 0
A16: Total | C16: =SUM(C15:C15) -> 5100000 | D16: =SUM(D15:D15) -> 0
A18: (3) Current liabilities
A19: (a) Trade Payables | B19: =Notes!A34 -> 4
A20: - Due to Micro and Small Enterprises | C20: 0 | D20: 0
A21: - Due to Others | C21: =Notes!$I$84 -> 523219.09 | D21: =Notes!$J$84 -> 0
A22: (b) Short-term Provisions and Statutory Liabilities | B22: =Notes!A87 -> 5 | C22: =Notes!$I$141 -> 6149763.8 | D22: =Notes!$J$141 -> 0
A23: Total | C23: =SUM(C20:C22) -> 6672982.9 | D23: =SUM(D20:D22) -> 0
A24: Total Equity and Liabilities | C24: =SUM(C12,C16,C23) -> 11594584 | D24: =SUM(D12,D16,D23) -> 0
A26: II. ASSETS
A27: (1) Non-current assets
A28: (a) Property, Plant and Equipment and Intangible Assets
A29: (i) Property, Plant and Equipment | B29: =Notes!A144 -> 6 | C29: =Notes!$I$149 -> 1234104.9 | D29: =Notes!$J$149 -> 0
A30: (b) Non-current Investments | C30: =Notes!$I$157 -> 0 | D30: =Notes!$J$157 -> 0
A31: (c) Deferred Tax Assets (net) | C31: =Notes!$I$165 -> 0 | D31: =Notes!$J$165 -> 0
A32: (d) Other Non-current Assets | C32: =Notes!$I$173 -> 0 | D32: =Notes!$J$173 -> 0
A33: Total | C33: =SUM(C29:C32) -> 1234104.9 | D33: =SUM(D29:D32) -> 0
A35: (2) Current assets
A36: (a) Trade Receivables | B36: 12 | C36: =Notes!$I$195 -> 9813353.9 | D36: =Notes!$J$195 -> 0
A37: (b) Cash and cash equivalents | B37: 13 | C37: =Notes!$I$203 -> 150192.98 | D37: =Notes!$J$203 -> 0
A38: (c) Inventories | B38: 14 | C38: =Notes!$I$211 -> 0 | D38: =Notes!$J$211 -> 0
A39: (d) Other Current Assets | B39: 15 | C39: =Notes!$I$220 -> 396932 | D39: =Notes!$J$220 -> 0
A40: Total | C40: =SUM(C36:C39) -> 10360479 | D40: =SUM(D36:D39) -> 0
A42: Total Assets | C42: =SUM(C33,C40) -> 11594584 | D42: =SUM(D33,D40) -> 0 | E42: =C42-C24 -> 0
A44: See accompanying notes to the financial statements
A46: As per our report of even date
A47: For R.K.Tantry & Co., | B47: For and on behalf of the Partners of
A48: Chartered Accountants | B48: KRTRIMAIQ COGNITIVE SOLUTIONS
A49: Firm's Registration No. 004335S
A53: Radhakrishna Tantry | B53: SRINIVAS RAO POLADI
A54: Partner | B54: PARTNER
A55: Membership No. 024012
A56: UDIN:
A57: Place: Bangalore | D57: Place: Bangalore
A58: Date: | D58: Date:

Sheet Fixed Assets
B2: KRTRIMAIQ COGNITIVE SOLUTIONS
B3: (Partnership Firm)
B4: Fixed Assets Schedule forming part of the Financial Statements
B6: Property, Plant and Equipment | L6: (In Rs)
B7: Name of Assets | C7: Gross Block | G7: Depreciation and Amortization | K7: Net Block | L7: Net Block
C8: As on | D8: Addition | E8: Deduction | F8: As on | G8: As on | H8: for the | I8: Deduction | J8: As on | K8: As on | L8: As on
C9: 45747 | F9: 46112 | G9: 45747 | H9: year | J9: 46112 | K9: 46112 | L9: 45747
B10: (i) Property, Plant and Equipment
B12: Computer- Laptop- IPad | C12: =TB!$B$116 -> 902257.32 | D12: =TB!$C$116 -> 84000 | E12: =TB!$D$116 -> 0 | F12: =C12+D12-E12 -> 986257.32 | G12: =0 -> 0 | H12: 0 | I12: =0 -> 0 | J12: =G12+H12-I12 -> 0 | K12: =F12-J12 -> 986257.32 | L12: =C12-G12 -> 902257.32
B13: Furniture and Fittings | C13: =TB!$B$117 -> 37201 | D13: =TB!$C$117 -> 0 | E13: =TB!$D$117 -> 0 | F13: =C13+D13-E13 -> 37201 | G13: =0 -> 0 | H13: 0 | I13: =0 -> 0 | J13: =G13+H13-I13 -> 0 | K13: =F13-J13 -> 37201 | L13: =C13-G13 -> 37201
B14: Mobile | C14: =TB!$B$118 -> 39683.6 | D14: =TB!$C$118 -> 0 | E14: =TB!$D$118 -> 0 | F14: =C14+D14-E14 -> 39683.6 | G14: =0 -> 0 | H14: 0 | I14: =0 -> 0 | J14: =G14+H14-I14 -> 0 | K14: =F14-J14 -> 39683.6 | L14: =C14-G14 -> 39683.6
B15: Office Equipments | C15: =TB!$B$119 -> 170963 | D15: =TB!$C$119 -> 0 | E15: =TB!$D$119 -> 0 | F15: =C15+D15-E15 -> 170963 | G15: =0 -> 0 | H15: 0 | I15: =0 -> 0 | J15: =G15+H15-I15 -> 0 | K15: =F15-J15 -> 170963 | L15: =C15-G15 -> 170963
B16: Total | C16: =SUM(C12:C15) -> 1150104.9 | D16: =SUM(D12:D15) -> 84000 | E16: =SUM(E12:E15) -> 0 | F16: =SUM(F12:F15) -> 1234104.9 | G16: =SUM(G12:G15) -> 0 | H16: =SUM(H12:H15) -> 0 | I16: =SUM(I12:I15) -> 0 | J16: =SUM(J12:J15) -> 0 | ... L16: =SUM(L12:L15) -> 1150104.9
B17: Previous Year

Sheet TB
A1: KRTRIMAIQ COGNITIVE SOLUTIONS - (2023-24)
A2: No. 98/A 3Rd Floor
A3: 30Th Cross,7Th Block Jayanagar
A4: Bangalore
A5: KARNATAKA
A6: 560082
A7: E-Mail : srinivasarao.poladi@krtri maiq.ai
A8: Trial Balance
A9: 1-Apr-25 to 31-Mar-26
A10: 9 | B10: KRTRIMAIQ COGNITIVE SOLUTIONS - (2023-24) - (from 1-Apr-24) - (from 1-Apr-25)
A11: Particulars | B11: 1-Apr-25 to 31-Mar-26
A12: 9 | B12: Opening | C12: Transactions | E12: Closing
A13: 9 | B13: Balance | C13: Debit | D13: Credit | E13: Balance
A14: Capital Account | B14: 9732791 | C14: 17133127 | D14: 5739336.1 | E14: 1661000.4
A15: Appropriation | C15: 2570893.2 | D15: 523992.84 | E15: 2046900.4
A16: Laxmi Poladi | B16: 1812735 | E16: 1812735
A17: Srinivas Rao Poladi | B17: 7920056 | C17: 1536715.2 | D17: 115343.23 | E17: 6498684
A18: Srinivas Rao Poladi - B1 Health | C18: 218775 | E18: 218775
A19: Srinivas Rao Poladi-Loan | D19: 5100000 | E19: 5100000
A20: Srinivas Rao Poladi - Sambhuthi | C20: 12806744 | E20: 12806744
A21: Current Liabilities | B21: 4727504.1 | C21: 71628266 | D21: 73573745 | E21: 6672982.9
A22: Duties & Taxes | B22: 90426 | C22: 8653328.2 | D22: 9298724.7 | E22: 735822.55
A23: CGST Input Tax | C23: 253369.33 | D23: 253369.33
A24: CGST Output Tax | C24: 2195020.1 | D24: 2195020.1
A25: GST Payable | B25: 90426 | C25: 3296167 | D25: 3941563.5 | E25: 735822.55
A26: IGST Input Tax | C26: 201182.32 | D26: 201182.32
A27: IGST Output Tax | C27: 259200 | D27: 259200
A28: SGST Input Tax | C28: 253369.33 | D28: 253369.33
A29: SGST Output Tax | C29: 2195020.1 | D29: 2195020.1
A30: Provisions | B30: 4661561 | C30: 58102964 | D30: 58855345 | E30: 5413941.3
A31: Expenses Payable | B31: 1711 | C31: 552694 | D31: 550983
A32: Akash Jena Expenses Payable | C32: 24566 | D32: 24566
A33: Arnab Ghosh Exp Payable | C33: 44183 | D33: 44183
A34: Arnav Kumar Exp | C34: 1776 | D34: 1776
A35: Arun Kumar K Exp Paybale | C35: 6316 | D35: 6316
A36: ASHISH SHUKLA Exp Paybale | C36: 17840 | D36: 17840
A37: Christy Joseph Exp Payable | C37: 38566 | D37: 38566
A38: Divyansh Chhablani Exp | B38: 1711 | C38: 16448 | D38: 14737
A39: Dushyant Chauhan Exp | C39: 800 | D39: 800
A40: Hemanth Ganta V V Expenses Payable | C40: 113064 | D40: 113064
A41: Jaishree R Exp Payable | C41: 1309 | D41: 1309
A42: Mohammed Rafeeq Expenses | C42: 500 | D42: 500
A43: Nikhil Kumar Expenses Payable | C43: 6979 | D43: 6979
A44: Om Prakash Narayan Gunalan- Exp | C44: 54627 | D44: 54627
A45: Parth Kumar Expenses. | C45: 13080 | D45: 13080
A46: Pasupuleti Surya Chandra Exp Payable | C46: 1500 | D46: 1500
A47: PAVITHRAA SHANMUGAM Exp Payable | C47: 1200 | D47: 1200
A48: Prajwal Nagaraja Exp | C48: 1800 | D48: 1800
A49: Rohit Bohira Exp Paybale | C49: 5749 | D49: 5749
A50: Rohit Kumar Bairy Exp Payable | C50: 2500 | D50: 2500
... A60: VELMULA SANATH REDDY Exp Payable | C60: 1500 | D60: 1500
A61: Professional Fee Payable | B61: 198900 | C61: 2739330 | D61: 2717621 | E61: 177191
A62: Salary Payable | B62: 4067743 | C62: 48269166 | D62: 48934613 | E62: 4733190
A63: Stipend Payable | B63: 55000 | C63: 585563 | D63: 566663 | E63: 36100
A64: EPF Payable - Admnistration Charges | D64: 8400 | E64: 8400
A65: EPF Payble - Employee Contribution | B65: 211495 | C65: 2086528 | D65: 1956339.7 | E65: 81306.7
A66: EPF Payble - Employer Contribution | B66: 85100 | C66: 1110608 | D66: 1173495 | E66: 147987
A67: Professional Tax on Salary | B67: 1200 | C67: 133600 | D67: 151600 | E67: 16800
A68: TDS on Professinal Charges | B68: 32150 | C68: 740091 | D68: 773833 | E68: 65892
A69: TDS on Professinal Charges- 2024-25 | B69: 10662 | C69: 10662
A70: TDS on Salary | C70: 1874722 | D70: 2021796.6 | E70: 147074.59
A71: Sundry Creditors | B71: 24482.89 | C71: 4871973.5 | D71: 5419675.5 | E71: 523219.09
A72: AINTREE TECH SOLUTIONS PRIVATE LIMITED | B72: 47047.11 | C72: 801131.3 | D72: 754084.19
A73: Amazon | C73: 17687 | D73: 17687
A74: AMAZON WEB SERVICES INDIA PRIVATE LIMITED | C74: 106140.49 | D74: 106140.49
A75: ANALYTICS INDIA MAGAZINE PRIVATE LIMITED | C75: 518000.01 | D75: 518000.01
A76: ANTHROPIC | C76: 176264.85 | D76: 176264.85
A77: APPYHAPPY SOFTWARE PRIVATE LIMITED | C77: 397 | D77: 397
A78: AUTHBRIDGE RESEARCH SERVICES PVT LTD | C78: 531 | D78: 531
A79: AV INFOLINE | C79: 10796.98 | D79: 10796.98
A80: BROWNE & MOHAN | C80: 1362500 | D80: 1632500 | E80: 270000
A81: CARE HEALTH INSURANCE LIMITED | C81: 28957.77 | D81: 28957.77
A82: CLICKTECH RETAIL PRIVATE LIMITED | C82: 329 | D82: 329
A83: CONFEDERATION OF INDIAN INDUSTRY | C83: 17700 | D83: 17700
A84: E2E Networks Limited | B84: 71530 | C84: 832000 | D84: 903530
A85: Futura Digiral Colour Press | C85: 25249 | D85: 25249
A86: HDFC ERGO GENERAL INSURANCE COMPANY LIMITED | C86: 5726.16 | D86: 5726.16
A87: HEYGEN TECHNOLOGY INC | C87: 83913.08 | D87: 83913.08
A88: Interglobe Aviation Limited | C88: 33143 | D88: 33143
A89: KHARESIYA BRANDS PRIVATE LIMITED | C89: 324 | D89: 324
A90: LA MARVELLA U O | C90: 846 | D90: 846
A91: Linkedin | C91: 79530.1 | D91: 79530.1
A92: MAKE MY TRIP (INDIA) PVT. LTD. | C92: 82 | D92: 82
A93: MANI ARTS | C93: 17051 | D93: 17051
A94: Medium Subscription | C94: 4298.93 | D94: 4298.93
A95: Mongo DB Subscription | C95: 10087.9 | D95: 10087.9
A96: M/S INFO EDGE INDIA LTD | C96: 177000 | D96: 177000
... A99: OpenAI Service | C99: 286418.6 | D99: 286418.6
A100: REDINGTON LIMITED | C100: 54610 | D100: 172829.09 | E100: 118219.09
A101: RETAILEZ PRIVATE LIMITED | C101: 1398 | D101: 1398
A102: RK Tantry & Co | C102: 15000 | D102: 150000 | E102: 135000
A103: SCORPZON TRADING PRIVATE LIMITED | C103: 1333.99 | D103: 1333.99
A104: SECURE EDGE SAFETY SYSTEMS | C104: 8089 | D104: 8089
A105: SIGNALHIRE C | C105: 25240.05 | D105: 25240.05
A106: SILICON LOGICS COMPUTER SOLUTIONS | C106: 21712 | D106: 21712
A107: SPICEJET LIMITED | C107: 5880 | D107: 5880
A108: SRI MANJUNATHA BATTERIES | C108: 6500 | D108: 6500
A109: The Magic Kreation | C109: 8240 | D109: 8240
A110: TISHYA TECHNOLOGIES LLP | C110: 9125 | D110: 9125
A111: TRAVELSTACK TECH LIMITED | C111: 668.26 | D111: 668.26
...

Sheet Notes
A1: KRTRIMAIQ COGNITIVE SOLUTIONS
A3: (Partnership Firm)
A4: Notes forming part of the Financial Statements
A6: 1 | B6: Capital Account | J6: (In Rs)
B7: Particulars | I7: 46112 | J7: 45747
B9: Less: Appropriation | I9: =-TB!$E$15 -> -2046900.4 | J9: =-TB!$B$15 -> 0
B10: Laxmi Poladi | I10: =TB!$E$16 -> 1812735
B11: Srinivas Rao Poladi | I11: =TB!$E$17 -> 6498684
B12: Less: Srinivas Rao Poladi - B1 Health | I12: =-TB!$E$18 -> -218775 | J12: =-TB!$B$18 -> 0
B13: Less: Srinivas Rao Poladi - Sambhuthi | I13: =-TB!$E$20 -> -12806744 | J13: =-TB!$B$20 -> 0
B15: Total | I15: =SUM(I9:I13) -> -6761000.4
A18: 2 | B18: Profit and Loss Account | J18: (In Rs)
B19: Particulars | I19: 46112 | J19: 45747
B21: Current year surplus/(deficit) | I21: ='P&L'!$C$28 -> 6582601.3 | J21: =0 -> 0
B23: Total | I23: =SUM(I21:I21) -> 6582601.3 | J23: =SUM(J21:J21) -> 0
A26: 3 | B26: Long-term Borrowings | J26: (In Rs)
B27: Particulars | I27: 46112 | J27: 45747
B29: Srinivas Rao Poladi-Loan | I29: =TB!$E$19 -> 5100000 | J29: =TB!$B$19 -> 0
B31: Total | I31: =SUM(I29:I29) -> 5100000 | J31: =SUM(J29:J29) -> 0
A34: 4 | B34: Trade Payables | J34: (In Rs)
B35: Particulars | I35: 46112 | J35: 45747
B37: Due to Micro and Small Enterprises | I37: =0 -> 0 | J37: =0 -> 0
B38: Due to Others
B39: AINTREE TECH SOLUTIONS PRIVATE LIMITED | I39: =TB!$E$72 -> 0
B40: Amazon | I40: =TB!$E$73 -> 0 | J40: =TB!$B$73 -> 0
B41: AMAZON WEB SERVICES INDIA PRIVATE LIMITED | I41: =TB!$E$74 -> 0 | J41: =TB!$B$74 -> 0
B42: ANALYTICS INDIA MAGAZINE PRIVATE LIMITED | I42: =TB!$E$75 -> 0 | J42: =TB!$B$75 -> 0
B43: ANTHROPIC | I43: =TB!$E$76 -> 0 | J43: =TB!$B$76 -> 0
B44: APPYHAPPY SOFTWARE PRIVATE LIMITED | I44: =TB!$E$77 -> 0 | J44: =TB!$B$77 -> 0
B45: AUTHBRIDGE RESEARCH SERVICES PVT LTD | I45: =TB!$E$78 -> 0 | J45: =TB!$B$78 -> 0
B46: AV INFOLINE | I46: =TB!$E$79 -> 0 | J46: =TB!$B$79 -> 0
B47: BROWNE & MOHAN | I47: =TB!$E$80 -> 270000 | J47: =TB!$B$80 -> 0
B48: CARE HEALTH INSURANCE LIMITED | I48: =TB!$E$81 -> 0 | J48: =TB!$B$81 -> 0
B49: CLICKTECH RETAIL PRIVATE LIMITED | I49: =TB!$E$82 -> 0 | J49: =TB!$B$82 -> 0
B50: CONFEDERATION OF INDIAN INDUSTRY | I50: =TB!$E$83 -> 0 | J50: =TB!$B$83 -> 0
B51: E2E Networks Limited | I51: =TB!$E$84 -> 0
B52: Futura Digiral Colour Press | I52: =TB!$E$85 -> 0 | J52: =TB!$B$85 -> 0
B53: HDFC ERGO GENERAL INSURANCE COMPANY LIMITED | I53: =TB!$E$86 -> 0 | J53: =TB!$B$86 -> 0
B54: HEYGEN TECHNOLOGY INC | I54: =TB!$E$87 -> 0 | J54: =TB!$B$87 -> 0
B55: Interglobe Aviation Limited | I55: =TB!$E$88 -> 0 | J55: =TB!$B$88 -> 0
B56: KHARESIYA BRANDS PRIVATE LIMITED | I56: =TB!$E$89 -> 0 | J56: =TB!$B$89 -> 0
B57: LA MARVELLA U O | I57: =TB!$E$90 -> 0 | J57: =TB!$B$90 -> 0
B58: Linkedin | I58: =TB!$E$91 -> 0 | J58: =TB!$B$91 -> 0
B59: MAKE MY TRIP (INDIA) PVT. LTD. | I59: =TB!$E$92 -> 0 | J59: =TB!$B$92 -> 0
B60: MANI ARTS | I60: =TB!$E$93 -> 0 | J60: =TB!$B$93 -> 0
B61: Medium Subscription | I61: =TB!$E$94 -> 0 | J61: =TB!$B$94 -> 0
B62: Mongo DB Subscription | I62: =TB!$E$95 -> 0 | J62: =TB!$B$95 -> 0
B63: M/S INFO EDGE INDIA LTD | I63: =TB!$E$96 -> 0 | J63: =TB!$B$96 -> 0
B64: M/S UNIVELL COMPUTERS | I64: =TB!$E$97 -> 0 | J64: =TB!$B$97 -> 0
B65: NATIONAL ASSOCIATION OF SOFTWARE AND SERVICE COMPANIES | I65: =TB!$E$98 -> 0 | J65: =TB!$B$98 -> 0
B66: OpenAI Service | I66: =TB!$E$99 -> 0 | J66: =TB!$B$99 -> 0
B67: REDINGTON LIMITED | I67: =TB!$E$100 -> 118219.09 | J67: =TB!$B$100 -> 0
B68: RETAILEZ PRIVATE LIMITED | I68: =TB!$E$101 -> 0 | J68: =TB!$B$101 -> 0
B69: RK Tantry & Co | I69: =TB!$E$102 -> 135000 | J69: =TB!$B$102 -> 0
B70: SCORPZON TRADING PRIVATE LIMITED | I70: =TB!$E$103 -> 0 | J70: =TB!$B$103 -> 0
B71: SECURE EDGE SAFETY SYSTEMS | I71: =TB!$E$104 -> 0 | J71: =TB!$B$104 -> 0
B72: SIGNALHIRE C | I72: =TB!$E$105 -> 0 | J72: =TB!$B$105 -> 0
B73: SILICON LOGICS COMPUTER SOLUTIONS | I73: =TB!$E$106 -> 0 | J73: =TB!$B$106 -> 0
B74: SPICEJET LIMITED | I74: =TB!$E$107 -> 0 | J74: =TB!$B$107 -> 0
B75: SRI MANJUNATHA BATTERIES | I75: =TB!$E$108 -> 0 | J75: =TB!$B$108 -> 0
B76: The Magic Kreation | I76: =TB!$E$109 -> 0 | J76: =TB!$B$109 -> 0
B77: TISHYA TECHNOLOGIES LLP | I77: =TB!$E$110 -> 0 | J77: =TB!$B$110 -> 0
B78: TRAVELSTACK TECH LIMITED | I78: =TB!$E$111 -> 0 | J78: =TB!$B$111 -> 0
B79: TRIDENT AUTO ENTERPRISES PRIVATE LIMITED | I79: =TB!$E$112 -> 0 | J79: =TB!$B$112 -> 0
B80: UDEMY INDIA LLP | I80: =TB!$E$113 -> 0 | J80: =TB!$B$113 -> 0
B81: UR COMPUTER | I81: =TB!$E$114 -> 0 | J81: =TB!$B$114 -> 0
B82: Opening balance adjustment / grouping difference | I82: =TB!$E$71-SUM(I39:I81) -> 0
B84: Total | I84: =SUM(I37:I82) -> 523219.09
A87: 5 | B87: Short-term Provisions and Statutory Liabilities | J87: (In Rs)
B88: Particulars | I88: 46112 | J88: 45747
B90: Duties & Taxes
B91: CGST Input Tax | I91: =TB!$E$23 -> 0 | J91: =TB!$B$23 -> 0
B92: CGST Output Tax | I92: =TB!$E$24 -> 0 | J92: =TB!$B$24 -> 0
B93: GST Payable | I93: =TB!$E$25 -> 735822.55
B94: IGST Input Tax | I94: =TB!$E$26 -> 0
B95: IGST Output Tax | I95: =TB!$E$27 -> 0 | J95: =TB!$B$27 -> 0
B96: SGST Input Tax | I96: =TB!$E$28 -> 0 | J96: =TB!$B$28 -> 0
B97: SGST Output Tax | I97: =TB!$E$29 -> 0 | J97: =TB!$B$29 -> 0
B98: Provisions
B99: Expenses Payable | I99: =TB!$E$31 -> 0
B100: Akash Jena Expenses Payable | I100: =TB!$E$32 -> 0 | J100: =TB!$B$32 -> 0
B101: Arnab Ghosh Exp Payable | I101: =TB!$E$33 -> 0 | J101: =TB!$B$33 -> 0
B102: Arnav Kumar Exp | I102: =TB!$E$34 -> 0 | J102: =TB!$B$34 -> 0
B103: Arun Kumar K Exp Paybale | I103: =TB!$E$35 -> 0 | J103: =TB!$B$35 -> 0
B104: ASHISH SHUKLA Exp Paybale | I104: =TB!$E$36 -> 0 | J104: =TB!$B$36 -> 0
B105: Christy Joseph Exp Payable | I105: =TB!$E$37 -> 0 | J105: =TB!$B$37 -> 0
B106: Divyansh Chhablani Exp | I106: =TB!$E$38 -> 0
B107: Dushyant Chauhan Exp | I107: =TB!$E$39 -> 0 | J107: =TB!$B$39 -> 0
B108: Hemanth Ganta V V Expenses Payable | I108: =TB!$E$40 -> 0 | J108: =TB!$B$40 -> 0
B109: Jaishree R Exp Payable | I109: =TB!$E$41 -> 0 | J109: =TB!$B$41 -> 0
B110: Mohammed Rafeeq Expenses | I110: =TB!$E$42 -> 0 | J110: =TB!$B$42 -> 0
B111: Nikhil Kumar Expenses Payable | I111: =TB!$E$43 -> 0 | J111: =TB!$B$43 -> 0
B112: Om Prakash Narayan Gunalan- Exp | I112: =TB!$E$44 -> 0 | J112: =TB!$B$44 -> 0
B113: Parth Kumar Expenses. | I113: =TB!$E$45 -> 0 | J113: =TB!$B$45 -> 0
B114: Pasupuleti Surya Chandra Exp Payable | I114: =TB!$E$46 -> 0 | J114: =TB!$B$46 -> 0
B115: PAVITHRAA SHANMUGAM Exp Payable | I115: =TB!$E$47 -> 0 | J115: =TB!$B$47 -> 0
B116: Prajwal Nagaraja Exp | I116: =TB!$E$48 -> 0 | J116: =TB!$B$48 -> 0
B117: Rohit Bohira Exp Paybale | I117: =TB!$E$49 -> 0 | J117: =TB!$B$49 -> 0
B118: Rohit Kumar Bairy Exp Payable | I118: =TB!$E$50 -> 0 | J118: =TB!$B$50 -> 0
B119: Sailesh Kumar K Expenses Payable | I119: =TB!$E$51 -> 0 | J119: =TB!$B$51 -> 0
...
